{
  "generated": "2026-06-18 10:12",
  "today": "2026-06-18",
  "sources": [
    {
      "short": "CERI",
      "name": "Sciences Po — CERI",
      "type": "university",
      "region": "Continental",
      "events_page": "https://www.sciencespo.fr/ceri/en/evenements.html",
      "flag": "🇫🇷",
      "country": "France",
      "city": "Paris",
      "lat": 48.857,
      "lng": 2.343,
      "count": 9,
      "status": "ok",
      "note": ""
    },
    {
      "short": "ASPI",
      "name": "Australian Strategic Policy Institute",
      "type": "think_tank",
      "region": "Indo-Pacific",
      "events_page": "https://www.aspi.org.au/events",
      "flag": "🇦🇺",
      "country": "Australia",
      "city": "Canberra",
      "lat": -35.281,
      "lng": 149.129,
      "count": 0,
      "status": "error",
      "note": "HTTPError: 403 Client Error: Forbidden for url: https://www.aspi.org.au/events/feed/"
    },
    {
      "short": "MERICS",
      "name": "Mercator Institute for China Studies",
      "type": "think_tank",
      "region": "Continental",
      "events_page": "https://merics.org/en/events",
      "flag": "🇩🇪",
      "country": "Germany",
      "city": "Berlin",
      "lat": 52.52,
      "lng": 13.405,
      "count": 5,
      "status": "ok",
      "note": ""
    },
    {
      "short": "DIIS",
      "name": "Danish Institute for International Studies",
      "type": "research_institute",
      "region": "Nordic",
      "events_page": "https://www.diis.dk/en/events",
      "flag": "🇩🇰",
      "country": "Denmark",
      "city": "Copenhagen",
      "lat": 55.676,
      "lng": 12.568,
      "count": 2,
      "status": "ok",
      "note": ""
    },
    {
      "short": "KCL/LCI",
      "name": "KCL — Lau China Institute",
      "type": "university",
      "region": "UK",
      "events_page": "https://www.kcl.ac.uk/lci/events",
      "flag": "🇬🇧",
      "country": "United Kingdom",
      "city": "London",
      "lat": 51.507,
      "lng": -0.128,
      "count": 1,
      "status": "ok",
      "note": ""
    },
    {
      "short": "KCL/War",
      "name": "KCL — Department of War Studies",
      "type": "university",
      "region": "UK",
      "events_page": "https://www.kcl.ac.uk/warstudies/events",
      "flag": "🇬🇧",
      "country": "United Kingdom",
      "city": "London",
      "lat": 51.507,
      "lng": -0.128,
      "count": 4,
      "status": "ok",
      "note": ""
    },
    {
      "short": "SIPRI",
      "name": "Stockholm International Peace Research Institute",
      "type": "research_institute",
      "region": "Nordic",
      "events_page": "https://www.sipri.org/news/upcoming",
      "flag": "🇸🇪",
      "country": "Sweden",
      "city": "Stockholm",
      "lat": 59.329,
      "lng": 18.069,
      "count": 4,
      "status": "ok",
      "note": ""
    },
    {
      "short": "Aarhus/PS",
      "name": "Aarhus University — Political Science",
      "type": "university",
      "region": "Nordic",
      "events_page": "https://ps.au.dk/en/current/events",
      "flag": "🇩🇰",
      "country": "Denmark",
      "city": "Aarhus",
      "lat": 56.162,
      "lng": 10.204,
      "count": 0,
      "status": "error",
      "note": "ConnectTimeout: HTTPSConnectionPool(host='ps.au.dk', port=443): Max retries exceeded with url: /en/current/events (Caused by ConnectTimeoutError(<HTTPSConnection(host='ps.au.dk', port=443) at 0x7fab1337cfb0>, 'Connection to ps.au.dk timed out. (connect timeout=25)'))"
    },
    {
      "short": "IISS",
      "name": "International Institute for Strategic Studies",
      "type": "think_tank",
      "region": "UK",
      "events_page": "https://www.iiss.org/events/",
      "flag": "🇬🇧",
      "country": "United Kingdom",
      "city": "London",
      "lat": 51.507,
      "lng": -0.128,
      "count": 0,
      "status": "manual",
      "note": "not auto-collected — open the site to check"
    },
    {
      "short": "ECFR",
      "name": "European Council on Foreign Relations",
      "type": "think_tank",
      "region": "Continental",
      "events_page": "https://ecfr.eu/events/",
      "flag": "🇩🇪",
      "country": "Germany",
      "city": "Berlin",
      "lat": 52.52,
      "lng": 13.405,
      "count": 1,
      "status": "ok",
      "note": ""
    },
    {
      "short": "ISDP",
      "name": "Institute for Security and Development Policy",
      "type": "research_institute",
      "region": "Nordic",
      "events_page": "https://www.isdp.eu/event/",
      "flag": "🇸🇪",
      "country": "Sweden",
      "city": "Stockholm",
      "lat": 59.329,
      "lng": 18.069,
      "count": 0,
      "status": "manual",
      "note": "not auto-collected — open the site to check"
    },
    {
      "short": "Cam/POLIS",
      "name": "Cambridge — Politics & International Studies (POLIS)",
      "type": "university",
      "region": "UK",
      "events_page": "https://www.polis.cam.ac.uk/events",
      "flag": "🇬🇧",
      "country": "United Kingdom",
      "city": "Cambridge",
      "lat": 52.205,
      "lng": 0.119,
      "count": 8,
      "status": "ok",
      "note": ""
    },
    {
      "short": "Cam/CfG",
      "name": "Cambridge — Centre for Geopolitics",
      "type": "university",
      "region": "UK",
      "events_page": "https://www.cfg.cam.ac.uk/events/",
      "flag": "🇬🇧",
      "country": "United Kingdom",
      "city": "Cambridge",
      "lat": 52.205,
      "lng": 0.119,
      "count": 4,
      "status": "ok",
      "note": ""
    },
    {
      "short": "EUISS",
      "name": "EU Institute for Security Studies",
      "type": "research_institute",
      "region": "Continental",
      "events_page": "https://www.iss.europa.eu/activities/events",
      "flag": "🇫🇷",
      "country": "France",
      "city": "Paris",
      "lat": 48.857,
      "lng": 2.343,
      "count": 1,
      "status": "ok",
      "note": ""
    },
    {
      "short": "CSIS",
      "name": "Center for Strategic and International Studies",
      "type": "think_tank",
      "region": "North America",
      "events_page": "https://www.csis.org/events",
      "flag": "🇺🇸",
      "country": "United States",
      "city": "Washington",
      "lat": 38.907,
      "lng": -77.037,
      "count": 17,
      "status": "ok",
      "note": ""
    },
    {
      "short": "GTI",
      "name": "Global Taiwan Institute",
      "type": "think_tank",
      "region": "North America",
      "events_page": "https://globaltaiwan.org/events/",
      "flag": "🇺🇸",
      "country": "United States",
      "city": "Washington",
      "lat": 38.907,
      "lng": -77.037,
      "count": 0,
      "status": "manual",
      "note": "not auto-collected — open the site to check"
    },
    {
      "short": "CEIAS",
      "name": "Central European Institute of Asian Studies",
      "type": "think_tank",
      "region": "Continental",
      "events_page": "https://ceias.eu/events/",
      "flag": "🇸🇰",
      "country": "Slovakia",
      "city": "Bratislava",
      "lat": 48.148,
      "lng": 17.107,
      "count": 0,
      "status": "manual",
      "note": "not auto-collected — open the site to check"
    },
    {
      "short": "UCPH/PS",
      "name": "University of Copenhagen — Political Science",
      "type": "university",
      "region": "Nordic",
      "events_page": "https://politicalscience.ku.dk/events/",
      "flag": "🇩🇰",
      "country": "Denmark",
      "city": "Copenhagen",
      "lat": 55.676,
      "lng": 12.568,
      "count": 1,
      "status": "ok",
      "note": ""
    },
    {
      "short": "CBS",
      "name": "Copenhagen Business School",
      "type": "university",
      "region": "Nordic",
      "events_page": "https://www.cbs.dk/en/events",
      "flag": "🇩🇰",
      "country": "Denmark",
      "city": "Copenhagen",
      "lat": 55.676,
      "lng": 12.568,
      "count": 9,
      "status": "ok",
      "note": ""
    },
    {
      "short": "FIIA",
      "name": "Finnish Institute of International Affairs",
      "type": "research_institute",
      "region": "Nordic",
      "events_page": "https://www.fiia.fi/en/events",
      "flag": "🇫🇮",
      "country": "Finland",
      "city": "Helsinki",
      "lat": 60.17,
      "lng": 24.941,
      "count": 0,
      "status": "manual",
      "note": "not auto-collected — open the site to check"
    },
    {
      "short": "NKK",
      "name": "Swedish National China Centre",
      "type": "research_institute",
      "region": "Nordic",
      "events_page": "https://kinacentrum.se/en/events/",
      "flag": "🇸🇪",
      "country": "Sweden",
      "city": "Stockholm",
      "lat": 59.329,
      "lng": 18.069,
      "count": 0,
      "status": "empty",
      "note": ""
    },
    {
      "short": "Lowy",
      "name": "Lowy Institute",
      "type": "think_tank",
      "region": "Indo-Pacific",
      "events_page": "https://www.lowyinstitute.org/events",
      "flag": "🇦🇺",
      "country": "Australia",
      "city": "Sydney",
      "lat": -33.869,
      "lng": 151.209,
      "count": 0,
      "status": "manual",
      "note": "not auto-collected — open the site to check"
    },
    {
      "short": "Oxf/China",
      "name": "Oxford University — China Centre",
      "type": "university",
      "region": "UK",
      "events_page": "https://www.chinacentre.ox.ac.uk/events",
      "flag": "🇬🇧",
      "country": "United Kingdom",
      "city": "Oxford",
      "lat": 51.755,
      "lng": -1.255,
      "count": 0,
      "status": "manual",
      "note": "not auto-collected — open the site to check"
    },
    {
      "short": "PISM",
      "name": "Polish Institute of International Affairs",
      "type": "research_institute",
      "region": "Continental",
      "events_page": "https://www.pism.pl/events",
      "flag": "🇵🇱",
      "country": "Poland",
      "city": "Warsaw",
      "lat": 52.232,
      "lng": 21.012,
      "count": 0,
      "status": "manual",
      "note": "not auto-collected — open the site to check"
    },
    {
      "short": "CEU/PS",
      "name": "Central European University — Political Science",
      "type": "university",
      "region": "Continental",
      "events_page": "https://events.ceu.edu/",
      "flag": "🇦🇹",
      "country": "Austria",
      "city": "Vienna",
      "lat": 48.208,
      "lng": 16.373,
      "count": 0,
      "status": "manual",
      "note": "not auto-collected — open the site to check"
    },
    {
      "short": "AAU/PS",
      "name": "Aalborg University — Politics & Society",
      "type": "university",
      "region": "Nordic",
      "events_page": "https://www.politics-society.aau.dk/news-and-events",
      "flag": "🇩🇰",
      "country": "Denmark",
      "city": "Aalborg",
      "lat": 57.048,
      "lng": 9.922,
      "count": 0,
      "status": "manual",
      "note": "not auto-collected — open the site to check"
    },
    {
      "short": "FUB/IPP",
      "name": "FU Berlin — Indo-Pacific Politics",
      "type": "university",
      "region": "Continental",
      "events_page": "https://www.polsoz.fu-berlin.de/en/polwiss/forschung/international/indo-pacific/",
      "flag": "🇩🇪",
      "country": "Germany",
      "city": "Berlin",
      "lat": 52.52,
      "lng": 13.405,
      "count": 0,
      "status": "manual",
      "note": "not auto-collected — open the site to check"
    },
    {
      "short": "CFHK",
      "name": "Committee for Freedom in Hong Kong Foundation",
      "type": "think_tank",
      "region": "North America",
      "events_page": "https://www.thecfhk.org/events",
      "flag": "🇺🇸",
      "country": "United States",
      "city": "Washington",
      "lat": 38.907,
      "lng": -77.037,
      "count": 0,
      "status": "manual",
      "note": "not auto-collected — open the site to check"
    },
    {
      "short": "Helsinki",
      "name": "University of Helsinki",
      "type": "university",
      "region": "Nordic",
      "events_page": "https://tapahtumat.helsinki.fi/en-fi",
      "flag": "🇫🇮",
      "country": "Finland",
      "city": "Helsinki",
      "lat": 60.17,
      "lng": 24.941,
      "count": 0,
      "status": "manual",
      "note": "not auto-collected — open the site to check"
    },
    {
      "short": "Tampere",
      "name": "Tampere University",
      "type": "university",
      "region": "Nordic",
      "events_page": "https://www.tuni.fi/en/news/events",
      "flag": "🇫🇮",
      "country": "Finland",
      "city": "Tampere",
      "lat": 61.498,
      "lng": 23.761,
      "count": 0,
      "status": "manual",
      "note": "not auto-collected — open the site to check"
    },
    {
      "short": "INDSR",
      "name": "Institute for National Defense and Security Research",
      "type": "research_institute",
      "region": "Indo-Pacific",
      "events_page": "https://indsr.org.tw/informations?uid=5&year=1&page=1",
      "flag": "🇹🇼",
      "country": "Taiwan",
      "city": "Taipei",
      "lat": 25.033,
      "lng": 121.565,
      "count": 0,
      "status": "manual",
      "note": "not auto-collected — open the site to check"
    },
    {
      "short": "NCCU/IIR",
      "name": "NCCU — Institute of International Relations",
      "type": "university",
      "region": "Indo-Pacific",
      "events_page": "https://iir.nccu.edu.tw/PageDoc?fid=7478",
      "flag": "🇹🇼",
      "country": "Taiwan",
      "city": "Taipei",
      "lat": 25.033,
      "lng": 121.565,
      "count": 0,
      "status": "manual",
      "note": "not auto-collected — open the site to check"
    },
    {
      "short": "TFD",
      "name": "Taiwan Foundation for Democracy",
      "type": "think_tank",
      "region": "Indo-Pacific",
      "events_page": "https://www.tfd.org.tw/en",
      "flag": "🇹🇼",
      "country": "Taiwan",
      "city": "Taipei",
      "lat": 25.033,
      "lng": 121.565,
      "count": 0,
      "status": "manual",
      "note": "not auto-collected — open the site to check"
    },
    {
      "short": "AS/IPS",
      "name": "Academia Sinica — Institute of Political Science",
      "type": "research_institute",
      "region": "Indo-Pacific",
      "events_page": "https://www.ipsas.sinica.edu.tw/學術活動/",
      "flag": "🇹🇼",
      "country": "Taiwan",
      "city": "Taipei",
      "lat": 25.033,
      "lng": 121.565,
      "count": 0,
      "status": "manual",
      "note": "not auto-collected — open the site to check"
    },
    {
      "short": "INPR",
      "name": "Institute for National Policy Research",
      "type": "think_tank",
      "region": "Indo-Pacific",
      "events_page": "https://www.inpr.org.tw/activitys?lang=zh-tw",
      "flag": "🇹🇼",
      "country": "Taiwan",
      "city": "Taipei",
      "lat": 25.033,
      "lng": 121.565,
      "count": 0,
      "status": "manual",
      "note": "not auto-collected — open the site to check"
    },
    {
      "short": "Prospect",
      "name": "The Prospect Foundation",
      "type": "think_tank",
      "region": "Indo-Pacific",
      "events_page": "https://www.pf.org.tw/en/pfen/24.html",
      "flag": "🇹🇼",
      "country": "Taiwan",
      "city": "Taipei",
      "lat": 25.033,
      "lng": 121.565,
      "count": 0,
      "status": "manual",
      "note": "not auto-collected — open the site to check"
    },
    {
      "short": "TAEF",
      "name": "Taiwan-Asia Exchange Foundation",
      "type": "think_tank",
      "region": "Indo-Pacific",
      "events_page": "https://www.taef.org/event",
      "flag": "🇹🇼",
      "country": "Taiwan",
      "city": "Taipei",
      "lat": 25.033,
      "lng": 121.565,
      "count": 0,
      "status": "manual",
      "note": "not auto-collected — open the site to check"
    },
    {
      "short": "CSPA",
      "name": "Cross-Strait Policy Association",
      "type": "think_tank",
      "region": "Indo-Pacific",
      "events_page": "https://www.twcspa.com/event",
      "flag": "🇹🇼",
      "country": "Taiwan",
      "city": "Taipei",
      "lat": 25.033,
      "lng": 121.565,
      "count": 0,
      "status": "manual",
      "note": "not auto-collected — open the site to check"
    }
  ],
  "events": [
    {
      "id": "f2f57ff5ed38",
      "title": "What Xi Got in Pyongyang | The Capital Cable #136",
      "url": "https://www.csis.org/events/what-xi-got-pyongyang-capital-cable-136",
      "source_key": "csis",
      "institution": "CSIS",
      "institution_full": "Center for Strategic and International Studies",
      "type": "think_tank",
      "region": "North America",
      "date": "2026-06-16",
      "date_end": null,
      "time": "09:30",
      "date_text": "",
      "location": null,
      "format": "in-person",
      "topics": [
        "Japan & Korea"
      ],
      "summary": "Image Photo: Pedro PARDO / AFP via Getty Images What Xi Got in Pyongyang | The Capital Cable #136 June 16, 2026 • 9:30 – 10:15 am EDT Hosted by Korea Chair",
      "first_seen": "2026-06-18",
      "country": "United States",
      "city": "Washington",
      "flag": "🇺🇸",
      "lat": 38.907,
      "lng": -77.037
    },
    {
      "id": "74b7e3b4539e",
      "title": "Annual Council Meeting 2026",
      "url": "https://ecfr.eu/event/annual-council-meeting-2026/",
      "source_key": "ecfr",
      "institution": "ECFR",
      "institution_full": "European Council on Foreign Relations",
      "type": "think_tank",
      "region": "Continental",
      "date": "2026-06-17",
      "date_end": "2026-06-18",
      "time": null,
      "date_text": "",
      "location": "Berlin",
      "format": "in-person",
      "topics": [],
      "summary": "17 Jun Annual Council Meeting 2026 17 June 2026 · ECFR Berlin The Annual Council Meeting 2026 will take place on 17-18 June 2026 in Vienna",
      "first_seen": "2026-05-16",
      "country": "Germany",
      "city": "Berlin",
      "flag": "🇩🇪",
      "lat": 52.52,
      "lng": 13.405
    },
    {
      "id": "3a8c9a66ee2a",
      "title": "Border Security and Defense Cooperation in North America: Addressing Emerging Challenges",
      "url": "https://www.csis.org/events/border-security-and-defense-cooperation-north-america-addressing-emerging-challenges",
      "source_key": "csis",
      "institution": "CSIS",
      "institution_full": "Center for Strategic and International Studies",
      "type": "think_tank",
      "region": "North America",
      "date": "2026-06-17",
      "date_end": null,
      "time": "09:00",
      "date_text": "",
      "location": null,
      "format": "in-person",
      "topics": [
        "Defence & military",
        "Security & intelligence",
        "NATO & alliances"
      ],
      "summary": "Border Security and Defense Cooperation in North America: Addressing Emerging Challenges June 17, 2026 • 9:00 am – 2:30 pm EDT Hosted by Americas Program Strengthening Vaccine Production and Access to Routine Immunizations in Sub-Saharan Africa |The CommonHealth Live! June 17, 2026 • 9:00 – 10:00 am EDT Hosted by The CSIS Bipartisan Alliance for Global Health Security U.S.-Canada Border Security: ",
      "first_seen": "2026-06-08",
      "country": "United States",
      "city": "Washington",
      "flag": "🇺🇸",
      "lat": 38.907,
      "lng": -77.037
    },
    {
      "id": "afebc2e4d6b9",
      "title": "NORAD Modernization and Continental Defense",
      "url": "https://www.csis.org/events/norad-modernization-and-continental-defense",
      "source_key": "csis",
      "institution": "CSIS",
      "institution_full": "Center for Strategic and International Studies",
      "type": "think_tank",
      "region": "North America",
      "date": "2026-06-17",
      "date_end": null,
      "time": "09:00",
      "date_text": "",
      "location": null,
      "format": "in-person",
      "topics": [
        "Defence & military",
        "Security & intelligence",
        "NATO & alliances"
      ],
      "summary": "Border Security and Defense Cooperation in North America: Addressing Emerging Challenges June 17, 2026 • 9:00 am – 2:30 pm EDT Hosted by Americas Program Strengthening Vaccine Production and Access to Routine Immunizations in Sub-Saharan Africa |The CommonHealth Live! June 17, 2026 • 9:00 – 10:00 am EDT Hosted by The CSIS Bipartisan Alliance for Global Health Security U.S.-Canada Border Security: ",
      "first_seen": "2026-06-15",
      "country": "United States",
      "city": "Washington",
      "flag": "🇺🇸",
      "lat": 38.907,
      "lng": -77.037
    },
    {
      "id": "d9840d747174",
      "title": "REPORT LAUNCH: Friendly Proliferation: A Virtual Report Discussion with Astrid Chevreuil",
      "url": "https://www.csis.org/events/report-launch-friendly-proliferation-virtual-report-discussion-astrid-chevreuil",
      "source_key": "csis",
      "institution": "CSIS",
      "institution_full": "Center for Strategic and International Studies",
      "type": "think_tank",
      "region": "North America",
      "date": "2026-06-17",
      "date_end": null,
      "time": "01:30",
      "date_text": "",
      "location": null,
      "format": "online",
      "topics": [
        "Japan & Korea",
        "Defence & military",
        "Nuclear & arms control"
      ],
      "summary": "Image Photo: South Korean Defense Ministry/Getty Images REPORT LAUNCH: Friendly Proliferation: A Virtual Report Discussion with Astrid Chevreuil June 17, 2026 • 1:30 – 2:30 pm EDT Hosted by Project on Nuclear Issues",
      "first_seen": "2026-06-11",
      "country": "United States",
      "city": "Washington",
      "flag": "🇺🇸",
      "lat": 38.907,
      "lng": -77.037
    },
    {
      "id": "9546eddeca2f",
      "title": "Strengthening Vaccine Production and Access to Routine Immunizations in Sub-Saharan Africa |The CommonHealth Live!",
      "url": "https://www.csis.org/events/strengthening-vaccine-production-and-access-routine-immunizations-sub-saharan-africa",
      "source_key": "csis",
      "institution": "CSIS",
      "institution_full": "Center for Strategic and International Studies",
      "type": "think_tank",
      "region": "North America",
      "date": "2026-06-17",
      "date_end": null,
      "time": "09:00",
      "date_text": "",
      "location": null,
      "format": "in-person",
      "topics": [
        "Defence & military",
        "Security & intelligence",
        "NATO & alliances"
      ],
      "summary": "Border Security and Defense Cooperation in North America: Addressing Emerging Challenges June 17, 2026 • 9:00 am – 2:30 pm EDT Hosted by Americas Program Strengthening Vaccine Production and Access to Routine Immunizations in Sub-Saharan Africa |The CommonHealth Live! June 17, 2026 • 9:00 – 10:00 am EDT Hosted by The CSIS Bipartisan Alliance for Global Health Security U.S.-Canada Border Security: ",
      "first_seen": "2026-06-11",
      "country": "United States",
      "city": "Washington",
      "flag": "🇺🇸",
      "lat": 38.907,
      "lng": -77.037
    },
    {
      "id": "c79155e15fcd",
      "title": "U.S.-Canada Border Security: Fireside Chat with Sec. Markwayne Mullin and Hon. Gary Anandasangaree",
      "url": "https://www.csis.org/events/us-canada-border-security-fireside-chat-sec-markwayne-mullin-and-hon-gary-anandasangaree",
      "source_key": "csis",
      "institution": "CSIS",
      "institution_full": "Center for Strategic and International Studies",
      "type": "think_tank",
      "region": "North America",
      "date": "2026-06-17",
      "date_end": null,
      "time": "09:00",
      "date_text": "",
      "location": null,
      "format": "in-person",
      "topics": [
        "Defence & military",
        "Security & intelligence",
        "NATO & alliances"
      ],
      "summary": "Border Security and Defense Cooperation in North America: Addressing Emerging Challenges June 17, 2026 • 9:00 am – 2:30 pm EDT Hosted by Americas Program Strengthening Vaccine Production and Access to Routine Immunizations in Sub-Saharan Africa |The CommonHealth Live! June 17, 2026 • 9:00 – 10:00 am EDT Hosted by The CSIS Bipartisan Alliance for Global Health Security U.S.-Canada Border Security: ",
      "first_seen": "2026-06-18",
      "country": "United States",
      "city": "Washington",
      "flag": "🇺🇸",
      "lat": 38.907,
      "lng": -77.037
    },
    {
      "id": "12d70e71764a",
      "title": "Was the G7 Summit in France a Success? | State of Play",
      "url": "https://www.csis.org/events/was-g7-summit-france-success-state-play",
      "source_key": "csis",
      "institution": "CSIS",
      "institution_full": "Center for Strategic and International Studies",
      "type": "think_tank",
      "region": "North America",
      "date": "2026-06-17",
      "date_end": null,
      "time": "05:30",
      "date_text": "",
      "location": null,
      "format": "in-person",
      "topics": [],
      "summary": "Image Photo: Mandel NGAN/AFP/Getty Images Was the G7 Summit in France a Success? | State of Play June 17, 2026 • 5:30 – 6:15 pm EDT Hosted by Geopolitics and Foreign Policy",
      "first_seen": "2026-06-18",
      "country": "United States",
      "city": "Washington",
      "flag": "🇺🇸",
      "lat": 38.907,
      "lng": -77.037
    },
    {
      "id": "c650e2ef3a47",
      "title": "A Decade of U.S.-Laos Comprehensive Partnership",
      "url": "https://www.csis.org/events/decade-us-laos-comprehensive-partnership",
      "source_key": "csis",
      "institution": "CSIS",
      "institution_full": "Center for Strategic and International Studies",
      "type": "think_tank",
      "region": "North America",
      "date": "2026-06-18",
      "date_end": null,
      "time": "10:30",
      "date_text": "",
      "location": null,
      "format": "in-person",
      "topics": [
        "Japan & Korea",
        "Nuclear & arms control"
      ],
      "summary": "Upcoming Events Image Photo: AR Creations/Adobe Stock A Decade of U.S.-Laos Comprehensive Partnership June 18, 2026 • 10:30 am – 12:00 pm EDT In Person Webcast Hosted by Southeast Asia Program Image Photo: Jung Yeon-je/AFP/Getty Images The Future of Extended Deterrence: Will Japan and Korea Go Nuclear? June 18, 2026 • 2:00 – 3:00 pm EDT In Person Webcast Hosted by Geopolitics and Foreign Policy Im",
      "first_seen": "2026-06-11",
      "country": "United States",
      "city": "Washington",
      "flag": "🇺🇸",
      "lat": 38.907,
      "lng": -77.037
    },
    {
      "id": "f791787292e2",
      "title": "Challenging balancing acts: Launch of Danish Foreign Policy Review 2026",
      "url": "https://www.diis.dk/en/event/challenging-balancing-acts-launch-of-danish-foreign-policy-review-2026",
      "source_key": "diis",
      "institution": "DIIS",
      "institution_full": "Danish Institute for International Studies",
      "type": "research_institute",
      "region": "Nordic",
      "date": "2026-06-18",
      "date_end": null,
      "time": null,
      "date_text": "",
      "location": null,
      "format": "in-person",
      "topics": [
        "Nordic & Baltic"
      ],
      "summary": "18 Jun Challenging balancing acts: Launch of Danish Foreign Policy Review 2026 DIIS Auditorium DIIS invites you to the launch of the 2026 edition of the Danish Foreign Policy Review",
      "first_seen": "2026-06-01",
      "country": "Denmark",
      "city": "Copenhagen",
      "flag": "🇩🇰",
      "lat": 55.676,
      "lng": 12.568
    },
    {
      "id": "124b8834c2c8",
      "title": "From Insight to Policy: Partnering with African Expertise to Inform U.S.–Africa Policy and Engagement",
      "url": "https://www.csis.org/events/insight-policy-partnering-african-expertise-inform-us-africa-policy-and-engagement",
      "source_key": "csis",
      "institution": "CSIS",
      "institution_full": "Center for Strategic and International Studies",
      "type": "think_tank",
      "region": "North America",
      "date": "2026-06-18",
      "date_end": null,
      "time": "10:30",
      "date_text": "",
      "location": null,
      "format": "in-person",
      "topics": [
        "Japan & Korea",
        "Nuclear & arms control"
      ],
      "summary": "Upcoming Events Image Photo: AR Creations/Adobe Stock A Decade of U.S.-Laos Comprehensive Partnership June 18, 2026 • 10:30 am – 12:00 pm EDT In Person Webcast Hosted by Southeast Asia Program Image Photo: Jung Yeon-je/AFP/Getty Images The Future of Extended Deterrence: Will Japan and Korea Go Nuclear? June 18, 2026 • 2:00 – 3:00 pm EDT In Person Webcast Hosted by Geopolitics and Foreign Policy Im",
      "first_seen": "2026-06-18",
      "country": "United States",
      "city": "Washington",
      "flag": "🇺🇸",
      "lat": 38.907,
      "lng": -77.037
    },
    {
      "id": "5caeb5f2f7e7",
      "title": "MERICS China-Frühstück für MdB-Mitarbeiter:innen",
      "url": "https://merics.org/en/events/merics-china-fruhstuck-fur-mdb-mitarbeiterinnen-3",
      "source_key": "merics",
      "institution": "MERICS",
      "institution_full": "Mercator Institute for China Studies",
      "type": "think_tank",
      "region": "Continental",
      "date": "2026-06-18",
      "date_end": null,
      "time": null,
      "date_text": "",
      "location": "Berlin",
      "format": "in-person",
      "topics": [
        "China"
      ],
      "summary": "MERICS China-Frühstück für MdB-Mitarbeiter:innen Jun. 18, 2026 Berlin",
      "first_seen": "2026-06-11",
      "country": "Germany",
      "city": "Berlin",
      "flag": "🇩🇪",
      "lat": 52.52,
      "lng": 13.405
    },
    {
      "id": "96bccd582fb5",
      "title": "Modernizing to Meet the Future Threat: A Conversation with Lieutenant General Eric Austin, USMC",
      "url": "https://www.csis.org/events/modernizing-meet-future-threat-conversation-lieutenant-general-eric-austin-usmc",
      "source_key": "csis",
      "institution": "CSIS",
      "institution_full": "Center for Strategic and International Studies",
      "type": "think_tank",
      "region": "North America",
      "date": "2026-06-18",
      "date_end": null,
      "time": "10:30",
      "date_text": "",
      "location": null,
      "format": "in-person",
      "topics": [
        "Defence & military",
        "Security & intelligence"
      ],
      "summary": "Next Up Webcast Modernizing to Meet the Future Threat: A Conversation with Lieutenant General Eric Austin, USMC Presented by Defense and Security June 18, 2026 • 10:30 – 11:30 am EDT",
      "first_seen": "2026-06-08",
      "country": "United States",
      "city": "Washington",
      "flag": "🇺🇸",
      "lat": 38.907,
      "lng": -77.037
    },
    {
      "id": "3d4363874f80",
      "title": "Nuclear Armed Hypersonic Missiles | HTK",
      "url": "https://www.csis.org/events/nuclear-armed-hypersonic-missiles-htk",
      "source_key": "csis",
      "institution": "CSIS",
      "institution_full": "Center for Strategic and International Studies",
      "type": "think_tank",
      "region": "North America",
      "date": "2026-06-18",
      "date_end": null,
      "time": "10:30",
      "date_text": "",
      "location": null,
      "format": "in-person",
      "topics": [
        "Japan & Korea",
        "Nuclear & arms control"
      ],
      "summary": "Upcoming Events Image Photo: AR Creations/Adobe Stock A Decade of U.S.-Laos Comprehensive Partnership June 18, 2026 • 10:30 am – 12:00 pm EDT In Person Webcast Hosted by Southeast Asia Program Image Photo: Jung Yeon-je/AFP/Getty Images The Future of Extended Deterrence: Will Japan and Korea Go Nuclear? June 18, 2026 • 2:00 – 3:00 pm EDT In Person Webcast Hosted by Geopolitics and Foreign Policy Im",
      "first_seen": "2026-06-15",
      "country": "United States",
      "city": "Washington",
      "flag": "🇺🇸",
      "lat": 38.907,
      "lng": -77.037
    },
    {
      "id": "84bc2cd4c8b5",
      "title": "Previous events and webinars",
      "url": "https://www.diis.dk/en/events/previous-events",
      "source_key": "diis",
      "institution": "DIIS",
      "institution_full": "Danish Institute for International Studies",
      "type": "research_institute",
      "region": "Nordic",
      "date": "2026-06-18",
      "date_end": null,
      "time": null,
      "date_text": "",
      "location": null,
      "format": "online",
      "topics": [
        "Nordic & Baltic"
      ],
      "summary": "Breadcrumb Home Events Events Share on Bluesky Share on LinkedIn Share on Facebook Share on X Mail this page Print this page Copy this page URL 18 Jun Challenging balancing acts: Launch of Danish Foreign Policy Review 2026 DIIS Auditorium DIIS invites you to the launch of the 2026 edition of the Danish Foreign Policy Review Previous events and webinars Contact Photo/illustration by Jette Mariboe, ",
      "first_seen": "2026-05-16",
      "country": "Denmark",
      "city": "Copenhagen",
      "flag": "🇩🇰",
      "lat": 55.676,
      "lng": 12.568
    },
    {
      "id": "547a8d71bf05",
      "title": "The Emerging Voices Series: Strategy, Security & Defence",
      "url": "https://www.kcl.ac.uk/events/the-emerging-voices-series-strategy-security-defence",
      "source_key": "kcl_war",
      "institution": "KCL/War",
      "institution_full": "KCL — Department of War Studies",
      "type": "university",
      "region": "UK",
      "date": "2026-06-18",
      "date_end": null,
      "time": "09:00",
      "date_text": "",
      "location": null,
      "format": "in-person",
      "topics": [
        "Defence & military",
        "Security & intelligence"
      ],
      "summary": "18 Jun The Emerging Voices Series: Strategy, Security & Defence 18 June 2026, 09:00 to 18:30 Security & Defence PLuS will host the Emerging Voices Series: Strategy, Security & Defence at King's… Browser does not support script.",
      "first_seen": "2026-06-11",
      "country": "United Kingdom",
      "city": "London",
      "flag": "🇬🇧",
      "lat": 51.507,
      "lng": -0.128
    },
    {
      "id": "5c2e033a3acb",
      "title": "The Future of Extended Deterrence: Will Japan and Korea Go Nuclear?",
      "url": "https://www.csis.org/events/future-extended-deterrence-will-japan-and-korea-go-nuclear",
      "source_key": "csis",
      "institution": "CSIS",
      "institution_full": "Center for Strategic and International Studies",
      "type": "think_tank",
      "region": "North America",
      "date": "2026-06-18",
      "date_end": null,
      "time": "10:30",
      "date_text": "",
      "location": null,
      "format": "in-person",
      "topics": [
        "Japan & Korea",
        "Nuclear & arms control"
      ],
      "summary": "Upcoming Events Image Photo: AR Creations/Adobe Stock A Decade of U.S.-Laos Comprehensive Partnership June 18, 2026 • 10:30 am – 12:00 pm EDT In Person Webcast Hosted by Southeast Asia Program Image Photo: Jung Yeon-je/AFP/Getty Images The Future of Extended Deterrence: Will Japan and Korea Go Nuclear? June 18, 2026 • 2:00 – 3:00 pm EDT In Person Webcast Hosted by Geopolitics and Foreign Policy Im",
      "first_seen": "2026-06-15",
      "country": "United States",
      "city": "Washington",
      "flag": "🇺🇸",
      "lat": 38.907,
      "lng": -77.037
    },
    {
      "id": "5a71f9e5b0b5",
      "title": "BIGFI/Finance Seminar with Darrell Duffie",
      "url": "https://www.cbs.dk/en/events/bigfifinance-seminar-darrell-duffie",
      "source_key": "cbs",
      "institution": "CBS",
      "institution_full": "Copenhagen Business School",
      "type": "university",
      "region": "Nordic",
      "date": "2026-06-19",
      "date_end": null,
      "time": null,
      "date_text": "",
      "location": "Copenhagen",
      "format": "in-person",
      "topics": [],
      "summary": "Event BIGFI/Finance Seminar with Darrell Duffie Date: 19 June 2026 Location: Copenhagen Business School Solbjerg Plads 3 2000 Frederiksberg Room: SPs03 The Department of Finance and BIGFI are proud to announce the upcoming seminar with Darrell Duffie from Stanford University View event BIGFI/Finance Seminar with Darrell Duffie",
      "first_seen": "2026-06-18",
      "country": "Denmark",
      "city": "Copenhagen",
      "flag": "🇩🇰",
      "lat": 55.676,
      "lng": 12.568
    },
    {
      "id": "284bb6d1f034",
      "title": "Invitation for PhD Defence - Oskar Arnt Juul",
      "url": "https://www.cbs.dk/en/events/invitation-phd-defence-oskar-arnt-juul",
      "source_key": "cbs",
      "institution": "CBS",
      "institution_full": "Copenhagen Business School",
      "type": "university",
      "region": "Nordic",
      "date": "2026-06-19",
      "date_end": null,
      "time": "04:07",
      "date_text": "",
      "location": null,
      "format": "online",
      "topics": [
        "Defence & military"
      ],
      "summary": "Event Invitation for PhD Defence - Oskar Arnt Juul Date: 19 June 2026 Location: Location: Porcelænshaven 26 Room: PH26.4.07 (fourth floor) Reception: Kitchen area of ECON (3rd floor) *The CBS PhD School will host a reception, which will take place immediately after the defence. There will be no online attendance Invitation for PhD defence View event Invitation for PhD Defence - Oskar Arnt Juul",
      "first_seen": "2026-06-15",
      "country": "Denmark",
      "city": "Copenhagen",
      "flag": "🇩🇰",
      "lat": 55.676,
      "lng": 12.568
    },
    {
      "id": "30aefb0788fd",
      "title": "Invitation for PhD Defence - Sara Vardi",
      "url": "https://www.cbs.dk/en/events/invitation-phd-defence-sara-vardi",
      "source_key": "cbs",
      "institution": "CBS",
      "institution_full": "Copenhagen Business School",
      "type": "university",
      "region": "Nordic",
      "date": "2026-06-22",
      "date_end": null,
      "time": null,
      "date_text": "",
      "location": null,
      "format": "in-person",
      "topics": [
        "Defence & military"
      ],
      "summary": "Event Invitation for PhD Defence - Sara Vardi Date: 22 June 2026 Location: Location: Kilen Room: Ks54(ground floor) Reception: SI Lunch room area Kl 2.75 (second floor) *The CBS PhD School will host a reception, which will take place immediately after the defence. Invitation for PhD defence View event Invitation for PhD Defence - Sara Vardi",
      "first_seen": "2026-06-08",
      "country": "Denmark",
      "city": "Copenhagen",
      "flag": "🇩🇰",
      "lat": 55.676,
      "lng": 12.568
    },
    {
      "id": "584faa778f97",
      "title": "Book Launch: 'Transatlantic Storms in Anglo-American Relations: How the Alliance Weathers Crises' with Dr William D. James",
      "url": "https://www.kcl.ac.uk/events/book-launch-transatlantic-storms-in-anglo-american-relations-how-the-alliance-weathers-crises-with-dr-william-d.-james",
      "source_key": "kcl_war",
      "institution": "KCL/War",
      "institution_full": "KCL — Department of War Studies",
      "type": "university",
      "region": "UK",
      "date": "2026-06-23",
      "date_end": null,
      "time": "12:00",
      "date_text": "",
      "location": null,
      "format": "in-person",
      "topics": [
        "NATO & alliances"
      ],
      "summary": "23 Jun Book Launch: 'Transatlantic Storms in Anglo-American Relations: How the Alliance Weathers Crises' with Dr William D. James 23 June 2026, 12:00 to 13:15 With President Trump's designs on Greenland and disputes over the Iran War, many argue that the… Browser does not support script.",
      "first_seen": "2026-06-11",
      "country": "United Kingdom",
      "city": "London",
      "flag": "🇬🇧",
      "lat": 51.507,
      "lng": -0.128
    },
    {
      "id": "e13b5665e715",
      "title": "Forum: China and Asia after neoliberal globalisation?",
      "url": "https://www.kcl.ac.uk/events/forum-china-and-asia-after-neoliberal-globalisation",
      "source_key": "kcl_lci",
      "institution": "KCL/LCI",
      "institution_full": "KCL — Lau China Institute",
      "type": "university",
      "region": "UK",
      "date": "2026-06-24",
      "date_end": null,
      "time": "16:00",
      "date_text": "",
      "location": null,
      "format": "in-person",
      "topics": [
        "China"
      ],
      "summary": "Events All Today This week This month Archive 24 Jun Forum: China and Asia after neoliberal globalisation? 24 June 2026, 16:00 to 17:30 Leading scholars and experts will discuss how changing geopolitical and economic dynamics are… Browser does not support script. Search Browser does not support script. Browser does not support script. China Week Explore our annual flagship event series Subscribe t",
      "first_seen": "2026-06-11",
      "country": "United Kingdom",
      "city": "London",
      "flag": "🇬🇧",
      "lat": 51.507,
      "lng": -0.128
    },
    {
      "id": "64ab67d9dbda",
      "title": "Invitation for PhD Defence - Danyang He",
      "url": "https://www.cbs.dk/en/events/invitation-phd-defence-danyang-he",
      "source_key": "cbs",
      "institution": "CBS",
      "institution_full": "Copenhagen Business School",
      "type": "university",
      "region": "Nordic",
      "date": "2026-06-24",
      "date_end": null,
      "time": null,
      "date_text": "",
      "location": null,
      "format": "in-person",
      "topics": [
        "Defence & military"
      ],
      "summary": "Event Invitation for PhD Defence - Danyang He Date: 24 June 2026 Location: Location: Kilen Room: Ks71 Reception: Kitchen area of IOA (4th floor) *The CBS PhD School will host a reception, which will take place immediately after the defence. Invitation for PhD Defence View event Invitation for PhD Defence - Danyang He",
      "first_seen": "2026-06-15",
      "country": "Denmark",
      "city": "Copenhagen",
      "flag": "🇩🇰",
      "lat": 55.676,
      "lng": 12.568
    },
    {
      "id": "af2c75feb503",
      "title": "MERICS Members Day 2026",
      "url": "https://merics.org/en/events/merics-members-day-2026",
      "source_key": "merics",
      "institution": "MERICS",
      "institution_full": "Mercator Institute for China Studies",
      "type": "think_tank",
      "region": "Continental",
      "date": "2026-06-24",
      "date_end": null,
      "time": null,
      "date_text": "",
      "location": "Berlin",
      "format": "in-person",
      "topics": [],
      "summary": "MERICS Members Day 2026 Jun. 24, 2026 Berlin Members only",
      "first_seen": "2026-04-19",
      "country": "Germany",
      "city": "Berlin",
      "flag": "🇩🇪",
      "lat": 52.52,
      "lng": 13.405
    },
    {
      "id": "f25f6e9c0da0",
      "title": "Online event: Defending Europe, deterring Russia",
      "url": "https://www.iss.europa.eu/activities/events/online-event-defending-europe-deterring-russia",
      "source_key": "euiss",
      "institution": "EUISS",
      "institution_full": "EU Institute for Security Studies",
      "type": "research_institute",
      "region": "Continental",
      "date": "2026-06-24",
      "date_end": null,
      "time": null,
      "date_text": "",
      "location": "Online",
      "format": "online",
      "topics": [
        "Russia & Ukraine",
        "Defence & military"
      ],
      "summary": "Online event: Defending Europe, deterring Russia How can Europe build a credible defence posture in an era of reduced US engagement? Join our live discussion. Events Jun 24 2026",
      "first_seen": "2026-06-18",
      "country": "France",
      "city": "Paris",
      "flag": "🇫🇷",
      "lat": 48.857,
      "lng": 2.343
    },
    {
      "id": "20c2bbb3a784",
      "title": "Three Nations, One Table: North American Agriculture under USMCA",
      "url": "https://www.csis.org/events/three-nations-one-table-north-american-agriculture-under-usmca",
      "source_key": "csis",
      "institution": "CSIS",
      "institution_full": "Center for Strategic and International Studies",
      "type": "think_tank",
      "region": "North America",
      "date": "2026-06-24",
      "date_end": null,
      "time": null,
      "date_text": "",
      "location": null,
      "format": "in-person",
      "topics": [],
      "summary": "Three Nations, One Table: North American Agriculture under USMCA Join the Americas Program for a conference on USMCA and the future of North American food and agriculture. Experts will discuss food affordability, the successes and challenges of agricultural integration, and the risks that broader trade tensions pose to the agreement’s agricultural framework ahead of the 2026 review. Event — June 2",
      "first_seen": "2026-06-15",
      "country": "United States",
      "city": "Washington",
      "flag": "🇺🇸",
      "lat": 38.907,
      "lng": -77.037
    },
    {
      "id": "68994a470b51",
      "title": "Data Centers and the Future of AI Infrastructure: Federal, Local, and Industry Perspectives",
      "url": "https://www.csis.org/events/data-centers-and-future-ai-infrastructure-federal-local-and-industry-perspectives",
      "source_key": "csis",
      "institution": "CSIS",
      "institution_full": "Center for Strategic and International Studies",
      "type": "think_tank",
      "region": "North America",
      "date": "2026-06-25",
      "date_end": null,
      "time": null,
      "date_text": "",
      "location": null,
      "format": "in-person",
      "topics": [
        "Security & intelligence"
      ],
      "summary": "Data Centers and the Future of AI Infrastructure: Federal, Local, and Industry Perspectives An event examining the intersection of artificial intelligence, national security, and data center infrastructure, featuring perspectives from industry leaders and local and federal government officials. Event — June 25, 2026",
      "first_seen": "2026-06-15",
      "country": "United States",
      "city": "Washington",
      "flag": "🇺🇸",
      "lat": 38.907,
      "lng": -77.037
    },
    {
      "id": "d74cbbd62ae3",
      "title": "Invitation for PhD Defence - Jing Wang",
      "url": "https://www.cbs.dk/en/events/invitation-phd-defence-jing-wang",
      "source_key": "cbs",
      "institution": "CBS",
      "institution_full": "Copenhagen Business School",
      "type": "university",
      "region": "Nordic",
      "date": "2026-06-25",
      "date_end": null,
      "time": null,
      "date_text": "",
      "location": null,
      "format": "in-person",
      "topics": [
        "Defence & military"
      ],
      "summary": "Event Invitation for PhD Defence - Jing Wang Date: 25 June 2026 Location: Location: Kilen Room: Ks71 Reception: Kitchen area of IOA (4th floor) *The CBS PhD School will host a reception, which will take place immediately after the defence. Invitation for PhD defence View event Invitation for PhD Defence - Jing Wang",
      "first_seen": "2026-06-15",
      "country": "Denmark",
      "city": "Copenhagen",
      "flag": "🇩🇰",
      "lat": 55.676,
      "lng": 12.568
    },
    {
      "id": "b9df614612f0",
      "title": "ASEAN in the Age of Artificial Intelligence (AI)",
      "url": "https://www.sciencespo.fr/ceri/en/events/asean-in-the-age-of-artificial-intelligence-ai",
      "source_key": "ceri",
      "institution": "CERI",
      "institution_full": "Sciences Po — CERI",
      "type": "university",
      "region": "Continental",
      "date": "2026-06-26",
      "date_end": null,
      "time": null,
      "date_text": "",
      "location": null,
      "format": "in-person",
      "topics": [
        "Security & intelligence"
      ],
      "summary": "Event organised as part of the Current Dynamics in Southeast Asia seminar.",
      "first_seen": "2026-06-11",
      "country": "France",
      "city": "Paris",
      "flag": "🇫🇷",
      "lat": 48.857,
      "lng": 2.343
    },
    {
      "id": "f093b2806aaf",
      "title": "BIGFI/Finance Seminar with Péter Kondor",
      "url": "https://www.cbs.dk/en/events/bigfifinance-seminar-peter-kondor",
      "source_key": "cbs",
      "institution": "CBS",
      "institution_full": "Copenhagen Business School",
      "type": "university",
      "region": "Nordic",
      "date": "2026-06-26",
      "date_end": null,
      "time": null,
      "date_text": "",
      "location": "London",
      "format": "in-person",
      "topics": [],
      "summary": "Event BIGFI/Finance Seminar with Péter Kondor Date: 26 June 2026 Location: Copenhagen Business School Solbjerg Plads 3 2000 Frederiksberg Room SPs03 The Department of Finance are proud to announce the upcoming seminar with Péter Kondor from London School of Economics and Political Science View event BIGFI/Finance Seminar with Péter Kondor",
      "first_seen": "2026-06-18",
      "country": "Denmark",
      "city": "Copenhagen",
      "flag": "🇩🇰",
      "lat": 55.676,
      "lng": 12.568
    },
    {
      "id": "2e64c6bbe7a5",
      "title": "Soutenance de thèse de M. Eric REPETTO - Programme de Science politique",
      "url": "https://www.sciencespo.fr/ceri/en/events/soutenance-these-eric-repetto-science-politique",
      "source_key": "ceri",
      "institution": "CERI",
      "institution_full": "Sciences Po — CERI",
      "type": "university",
      "region": "Continental",
      "date": "2026-06-26",
      "date_end": null,
      "time": null,
      "date_text": "",
      "location": "Paris",
      "format": "in-person",
      "topics": [],
      "summary": "M. Eric REPETTODiscipline : Science politiqueSujet : Writing sovereignty from without: the role of private (digital) actors in constructing sovereign discourse in Australia and the European UnionJury : Stephane BAELE, Thierry BALZACQ (Directeur de recherche), Kristin Anabel EGGELING, Frédéric RAMEL, Swati SRIVASTAVACentre de recherche : CERILa soutenance publique aura lieu le 26/06/2026 à 9h, en s",
      "first_seen": "2026-05-07",
      "country": "France",
      "city": "Paris",
      "flag": "🇫🇷",
      "lat": 48.857,
      "lng": 2.343
    },
    {
      "id": "b120161e7510",
      "title": "Critical Minerals, Commodities and Infrastructure in Contemporary Africa",
      "url": "https://www.sciencespo.fr/ceri/en/events/critical-minerals-commodities-and-infrastructure-in-contemporary-africa",
      "source_key": "ceri",
      "institution": "CERI",
      "institution_full": "Sciences Po — CERI",
      "type": "university",
      "region": "Continental",
      "date": "2026-06-29",
      "date_end": null,
      "time": null,
      "date_text": "",
      "location": "Oxford",
      "format": "in-person",
      "topics": [
        "Economic security"
      ],
      "summary": "In-person event organised with the support of the Calouste Gulbenkian Foundation and the Oxford Martin Programme on African Governance, Oxford Martin School",
      "first_seen": "2026-06-18",
      "country": "France",
      "city": "Paris",
      "flag": "🇫🇷",
      "lat": 48.857,
      "lng": 2.343
    },
    {
      "id": "59020b42f876",
      "title": "Définir la minorité",
      "url": "https://www.sciencespo.fr/ceri/en/events/definir-la-minorite",
      "source_key": "ceri",
      "institution": "CERI",
      "institution_full": "Sciences Po — CERI",
      "type": "university",
      "region": "Continental",
      "date": "2026-06-29",
      "date_end": null,
      "time": null,
      "date_text": "",
      "location": null,
      "format": "hybrid",
      "topics": [],
      "summary": "Séminaire hybride organisé dans le cadre du séminaire Sciences sociales et psychanalyse.",
      "first_seen": "2026-05-28",
      "country": "France",
      "city": "Paris",
      "flag": "🇫🇷",
      "lat": 48.857,
      "lng": 2.343
    },
    {
      "id": "ffe96ee70131",
      "title": "Launch of the French-Brazilian AURELA Research Project",
      "url": "https://www.sciencespo.fr/ceri/en/events/launch-of-the-french-brazilian-aurela-research-project",
      "source_key": "ceri",
      "institution": "CERI",
      "institution_full": "Sciences Po — CERI",
      "type": "university",
      "region": "Continental",
      "date": "2026-06-29",
      "date_end": null,
      "time": null,
      "date_text": "",
      "location": null,
      "format": "in-person",
      "topics": [
        "Security & intelligence"
      ],
      "summary": "AURELA is a four-year Franco-Brazilian research program funded by CAPES-COFECUB and bringing together six universities in Brazil and France. The program explores key challenges in EU–Latin America relations, focusing on sustainability, security and emerging technologies, and democratic governance.",
      "first_seen": "2026-06-11",
      "country": "France",
      "city": "Paris",
      "flag": "🇫🇷",
      "lat": 48.857,
      "lng": 2.343
    },
    {
      "id": "b28e5ffac614",
      "title": "Soutenance de thèse de Mme Doha LKASMI - Programme de Science politique",
      "url": "https://www.sciencespo.fr/ceri/en/events/soutenance-these-doha-lkasmi-science-politique",
      "source_key": "ceri",
      "institution": "CERI",
      "institution_full": "Sciences Po — CERI",
      "type": "university",
      "region": "Continental",
      "date": "2026-06-29",
      "date_end": null,
      "time": null,
      "date_text": "",
      "location": "Paris",
      "format": "in-person",
      "topics": [],
      "summary": "Mme Doha LKASMIDiscipline : Science politiqueSujet : Le Sahara de sa Majesté : généalogie des revendications sahariennes comme grande stratégie du Maroc de 1956 à nos joursJury : Mohamed‐Ali ADRAOUI, Thierry BALZACQ (Directeur de recherche), Manon‐Nour TANNOUS, Michael WILLIS, Jonathan WYRTZENCentre de recherche : CERILa soutenance publique aura lieu le 29/06/2026 à 9h, en salle Goguel (56 rue des",
      "first_seen": "2026-05-15",
      "country": "France",
      "city": "Paris",
      "flag": "🇫🇷",
      "lat": 48.857,
      "lng": 2.343
    },
    {
      "id": "27da400e100f",
      "title": "2026 Global Security Forum, America at 250: A Defining Moment for American Statecraft and Military Power",
      "url": "https://www.csis.org/events/2026-global-security-forum-america-250-defining-moment-american-statecraft-and-military",
      "source_key": "csis",
      "institution": "CSIS",
      "institution_full": "Center for Strategic and International Studies",
      "type": "think_tank",
      "region": "North America",
      "date": "2026-06-30",
      "date_end": null,
      "time": null,
      "date_text": "",
      "location": null,
      "format": "in-person",
      "topics": [
        "Defence & military",
        "Security & intelligence"
      ],
      "summary": "2026 Global Security Forum, America at 250: A Defining Moment for American Statecraft and Military Power CSIS' flagship Defense and Security Forum will convene leaders from government, industry, finance, and academia to discuss how American statecraft and military power can drive strategic advantage in the years ahead. Event — June 30, 2026",
      "first_seen": "2026-06-15",
      "country": "United States",
      "city": "Washington",
      "flag": "🇺🇸",
      "lat": 38.907,
      "lng": -77.037
    },
    {
      "id": "375a05e9f1c6",
      "title": "MERICS Closed-door Workshop: China’s Advancements in New Semiconductor Technologies and Their Implications for Europe",
      "url": "https://merics.org/en/events/merics-closed-door-workshop-chinas-advancements-new-semiconductor-technologies-and-their",
      "source_key": "merics",
      "institution": "MERICS",
      "institution_full": "Mercator Institute for China Studies",
      "type": "think_tank",
      "region": "Continental",
      "date": "2026-06-30",
      "date_end": null,
      "time": null,
      "date_text": "",
      "location": "Berlin",
      "format": "in-person",
      "topics": [
        "China",
        "Economic security"
      ],
      "summary": "Industrial Policy and Technology MERICS Closed-door Workshop: China’s Advancements in New Semiconductor Technologies and Their Implications for Europe Jun. 30, 2026 Berlin",
      "first_seen": "2026-06-11",
      "country": "Germany",
      "city": "Berlin",
      "flag": "🇩🇪",
      "lat": 52.52,
      "lng": 13.405
    },
    {
      "id": "cf471e76b2e0",
      "title": "Patriotic Capital: Financing Industrial Strength and Security | 2026 Global Security Forum",
      "url": "https://www.csis.org/events/patriotic-capital-financing-industrial-strength-and-security-2026-global-security-forum",
      "source_key": "csis",
      "institution": "CSIS",
      "institution_full": "Center for Strategic and International Studies",
      "type": "think_tank",
      "region": "North America",
      "date": "2026-06-30",
      "date_end": null,
      "time": null,
      "date_text": "",
      "location": null,
      "format": "in-person",
      "topics": [
        "Security & intelligence",
        "Economic security"
      ],
      "summary": "Patriotic Capital: Financing Industrial Strength and Security | 2026 Global Security Forum How can the United States marshal private capital and modernize investment authorities to strengthen national security, from advanced technologies and energy to critical minerals and resilient supply chains? Event — June 30, 2026",
      "first_seen": "2026-06-18",
      "country": "United States",
      "city": "Washington",
      "flag": "🇺🇸",
      "lat": 38.907,
      "lng": -77.037
    },
    {
      "id": "1c985623c6a7",
      "title": "BOOK LAUNCH: Regenerating Learning: Permaculture for Sustainability Learning at Business Schools and Beyond",
      "url": "https://www.cbs.dk/en/events/book-launch-regenerating-learning-permaculture-sustainability-learning-business-schools-and",
      "source_key": "cbs",
      "institution": "CBS",
      "institution_full": "Copenhagen Business School",
      "type": "university",
      "region": "Nordic",
      "date": "2026-07-01",
      "date_end": null,
      "time": null,
      "date_text": "",
      "location": null,
      "format": "in-person",
      "topics": [],
      "summary": "Event BOOK LAUNCH: Regenerating Learning: Permaculture for Sustainability Learning at Business Schools and Beyond Date: 1 July 2026 Location: CBS Kilen and Permahaven Join us as we explore how permaculture can support student engagement with nature in the newly published book by Maribel Blasco and Isabel Froes and illustrated by Albina Dioba. View event BOOK LAUNCH: Regenerating Learning: Permacul",
      "first_seen": "2026-06-18",
      "country": "Denmark",
      "city": "Copenhagen",
      "flag": "🇩🇰",
      "lat": 55.676,
      "lng": 12.568
    },
    {
      "id": "cc8f9b814e62",
      "title": "Advancing Economic Security Forum 2026",
      "url": "https://merics.org/en/events/advancing-economic-security-forum-2026",
      "source_key": "merics",
      "institution": "MERICS",
      "institution_full": "Mercator Institute for China Studies",
      "type": "think_tank",
      "region": "Continental",
      "date": "2026-07-02",
      "date_end": null,
      "time": null,
      "date_text": "",
      "location": "Berlin",
      "format": "in-person",
      "topics": [
        "Security & intelligence",
        "Economic security"
      ],
      "summary": "Geopolitics Advancing Economic Security Forum 2026 Jul. 02, 2026 Berlin",
      "first_seen": "2026-06-11",
      "country": "Germany",
      "city": "Berlin",
      "flag": "🇩🇪",
      "lat": 52.52,
      "lng": 13.405
    },
    {
      "id": "c474b6bb82e8",
      "title": "Politicizing Business: How Firms Are Made to Serve the Party-State in China",
      "url": "https://www.sciencespo.fr/ceri/en/events/politicizing-business-how-firms-are-made-to-serve-the-party-state-in-china",
      "source_key": "ceri",
      "institution": "CERI",
      "institution_full": "Sciences Po — CERI",
      "type": "university",
      "region": "Continental",
      "date": "2026-07-06",
      "date_end": null,
      "time": null,
      "date_text": "",
      "location": null,
      "format": "in-person",
      "topics": [
        "China"
      ],
      "summary": "In person event organised as part of the \"International Political Economy\" research group",
      "first_seen": "2026-05-21",
      "country": "France",
      "city": "Paris",
      "flag": "🇫🇷",
      "lat": 48.857,
      "lng": 2.343
    },
    {
      "id": "c7e69a85a250",
      "title": "Sixteenth Annual South China Sea Conference",
      "url": "https://www.csis.org/events/sixteenth-annual-south-china-sea-conference",
      "source_key": "csis",
      "institution": "CSIS",
      "institution_full": "Center for Strategic and International Studies",
      "type": "think_tank",
      "region": "North America",
      "date": "2026-07-07",
      "date_end": null,
      "time": null,
      "date_text": "",
      "location": null,
      "format": "in-person",
      "topics": [
        "China",
        "Indo-Pacific"
      ],
      "summary": "Sixteenth Annual South China Sea Conference This full-day conference will feature keynote addresses and in-depth panel discussions on recent developments in disputed waters and the importance of the 10-year anniversary of the landmark South China Sea arbitration. Event — July 7, 2026",
      "first_seen": "2026-06-18",
      "country": "United States",
      "city": "Washington",
      "flag": "🇺🇸",
      "lat": 38.907,
      "lng": -77.037
    },
    {
      "id": "a73a2f21e6c0",
      "title": "Energy Security and Global South Perspectives",
      "url": "https://www.kcl.ac.uk/events/energy-security-and-global-south-perspectives",
      "source_key": "kcl_war",
      "institution": "KCL/War",
      "institution_full": "KCL — Department of War Studies",
      "type": "university",
      "region": "UK",
      "date": "2026-07-08",
      "date_end": null,
      "time": "09:30",
      "date_text": "",
      "location": null,
      "format": "in-person",
      "topics": [
        "Security & intelligence",
        "Climate & security"
      ],
      "summary": "8 Jul Energy Security and Global South Perspectives 8 July 2026, 09:30 to 9 July 2026, 16:00 A two-day event Browser does not support script.",
      "first_seen": "2026-06-11",
      "country": "United Kingdom",
      "city": "London",
      "flag": "🇬🇧",
      "lat": 51.507,
      "lng": -0.128
    },
    {
      "id": "8fb487ef535b",
      "title": "Loyalties-in-Between: Overseas Chinese Identity and the Chinese Communist Party",
      "url": "https://www.sciencespo.fr/ceri/en/events/loyalties-in-between-overseas-chinese-identity-and-the-chinese-communist-party",
      "source_key": "ceri",
      "institution": "CERI",
      "institution_full": "Sciences Po — CERI",
      "type": "university",
      "region": "Continental",
      "date": "2026-07-10",
      "date_end": null,
      "time": null,
      "date_text": "",
      "location": null,
      "format": "in-person",
      "topics": [
        "China"
      ],
      "summary": "Prof Tsai Wen-Hsuan will present his current work on the Chinese Communist Party's united front work towards overseas Chinese in Southeast Asia over the past century.",
      "first_seen": "2026-06-18",
      "country": "France",
      "city": "Paris",
      "flag": "🇫🇷",
      "lat": 48.857,
      "lng": 2.343
    },
    {
      "id": "558b70de024f",
      "title": "Book Launch: 'Bytes and Bullets: Global Rivalries, Private Tech, and the New Shape of Modern Warfare' with Steve Feldstein",
      "url": "https://www.kcl.ac.uk/events/book-launch-bytes-and-bullets-global-rivalries-private-tech-and-the-new-shape-of-modern-warfare-with-steven-feldstein",
      "source_key": "kcl_war",
      "institution": "KCL/War",
      "institution_full": "KCL — Department of War Studies",
      "type": "university",
      "region": "UK",
      "date": "2026-07-15",
      "date_end": null,
      "time": "17:00",
      "date_text": "",
      "location": null,
      "format": "in-person",
      "topics": [
        "Defence & military"
      ],
      "summary": "15 Jul Book Launch: 'Bytes and Bullets: Global Rivalries, Private Tech, and the New Shape of Modern Warfare' with Steve Feldstein 15 July 2026, 17:00 to 18:15 The race to develop and acquire cutting-edge innovations is playing a major role in shaping how… Browser does not support script.",
      "first_seen": "2026-06-18",
      "country": "United Kingdom",
      "city": "London",
      "flag": "🇬🇧",
      "lat": 51.507,
      "lng": -0.128
    },
    {
      "id": "bd4acac8adce",
      "title": "Climate Risks and Expected Returns",
      "url": "https://www.cbs.dk/en/events/climate-risks-and-expected-returns",
      "source_key": "cbs",
      "institution": "CBS",
      "institution_full": "Copenhagen Business School",
      "type": "university",
      "region": "Nordic",
      "date": "2026-08-24",
      "date_end": null,
      "time": null,
      "date_text": "",
      "location": null,
      "format": "in-person",
      "topics": [
        "Climate & security"
      ],
      "summary": "Event Climate Risks and Expected Returns Date: 24 August 2026 Location: Scandic Falkoner Falkoner Allé 9 2000 Frederiksberg On August 24, 2026, the Council for Return Expectations and Pension Research Centre (PeRCent) invites you to a conference on Climate Risk and Expected Returns… View event Climate Risks and Expected Returns",
      "first_seen": "2026-06-18",
      "country": "Denmark",
      "city": "Copenhagen",
      "flag": "🇩🇰",
      "lat": 55.676,
      "lng": 12.568
    },
    {
      "id": "9be537805427",
      "title": "Workshop: AI for business growth",
      "url": "https://www.cbs.dk/en/events/workshop-ai-business-growth",
      "source_key": "cbs",
      "institution": "CBS",
      "institution_full": "Copenhagen Business School",
      "type": "university",
      "region": "Nordic",
      "date": "2026-08-25",
      "date_end": null,
      "time": null,
      "date_text": "",
      "location": null,
      "format": "in-person",
      "topics": [
        "Nordic & Baltic"
      ],
      "summary": "Event Workshop: AI for business growth Date: 25 August 2026 Location: CBS Howitzvej 60, 6th Floor 2000 Frederiksberg Want to understand how AI can create measurable business value for your company? Join this practical workshop to learn how Danish SMEs are using AI to improve… View event Workshop: AI for business growth",
      "first_seen": "2026-06-18",
      "country": "Denmark",
      "city": "Copenhagen",
      "flag": "🇩🇰",
      "lat": 55.676,
      "lng": 12.568
    },
    {
      "id": "28e361c5eee0",
      "title": "Retour du Kenya. Enquête sur le personnel du siège des Nations Unies à Nairobi",
      "url": "https://www.sciencespo.fr/ceri/en/events/retour-du-kenya-enquete-sur-le-personnel-du-siege-des-nations-unies-a-nairobi",
      "source_key": "ceri",
      "institution": "CERI",
      "institution_full": "Sciences Po — CERI",
      "type": "university",
      "region": "Continental",
      "date": "2026-09-10",
      "date_end": null,
      "time": null,
      "date_text": "",
      "location": null,
      "format": "in-person",
      "topics": [],
      "summary": "Evènement en présentiel organisé dans le cadre du séminaire \"Retour de Terrain\".",
      "first_seen": "2026-06-18",
      "country": "France",
      "city": "Paris",
      "flag": "🇫🇷",
      "lat": 48.857,
      "lng": 2.343
    },
    {
      "id": "7368f8f3b1f8",
      "title": "MERICS European China Talent Program 2026",
      "url": "https://merics.org/en/events/merics-european-china-talent-program-2026",
      "source_key": "merics",
      "institution": "MERICS",
      "institution_full": "Mercator Institute for China Studies",
      "type": "think_tank",
      "region": "Continental",
      "date": "2026-09-22",
      "date_end": null,
      "time": null,
      "date_text": "",
      "location": "Berlin",
      "format": "in-person",
      "topics": [
        "China"
      ],
      "summary": "MERICS European China Talent Program 2026 The Call for Application for 2026 is open. Please find more information here. Sep. 22, 2026 Berlin",
      "first_seen": "2026-04-26",
      "country": "Germany",
      "city": "Berlin",
      "flag": "🇩🇪",
      "lat": 52.52,
      "lng": 13.405
    },
    {
      "id": "cb4bee707c42",
      "title": "t. 2026 The 6th Nordic Political Behavior Workshop Workshop taking place in the Department of Political Science, University of Copenhagen, Denmark, on…",
      "url": "https://politicalscience.ku.dk/events/2026/the-6th-nordic-political-behavior-workshop/",
      "source_key": "ku_polsci",
      "institution": "UCPH/PS",
      "institution_full": "University of Copenhagen — Political Science",
      "type": "university",
      "region": "Nordic",
      "date": "2026-09-25",
      "date_end": null,
      "time": null,
      "date_text": "",
      "location": "Copenhagen",
      "format": "in-person",
      "topics": [
        "Nordic & Baltic"
      ],
      "summary": "Department of Political Science Department of Political Science About the department Staff Research Education Press Contact us Faculty of Social Sciences English Events Calendar and events Events related to the Department of Political Science. The calendar is not necessary comprehensive, but we try to display all events that are directed towards an English-speaking audience. 19 June 2026, 10:00-13",
      "first_seen": "2026-05-21",
      "country": "Denmark",
      "city": "Copenhagen",
      "flag": "🇩🇰",
      "lat": 55.676,
      "lng": 12.568
    },
    {
      "id": "c154c660d3e5",
      "title": "2026 Stockholm Forum on Peace and Development",
      "url": "https://www.sipri.org/events/2026/2026-stockholm-forum-peace-and-development",
      "source_key": "sipri",
      "institution": "SIPRI",
      "institution_full": "Stockholm International Peace Research Institute",
      "type": "research_institute",
      "region": "Nordic",
      "date": "2026-11-03",
      "date_end": null,
      "time": null,
      "date_text": "",
      "location": "Stockholm",
      "format": "in-person",
      "topics": [],
      "summary": "3 November 2026 2026 Stockholm Forum on Peace and Development SIPRI will host the 2026 Stockholm Forum on the theme ‘From Rupture to Repair: New Visions for Peace and Development’.",
      "first_seen": "2026-04-28",
      "country": "Sweden",
      "city": "Stockholm",
      "flag": "🇸🇪",
      "lat": 59.329,
      "lng": 18.069
    },
    {
      "id": "38253297ce7c",
      "title": "Annual Lectures",
      "url": "https://www.polis.cam.ac.uk/events/annual-lectures",
      "source_key": "cam_polis",
      "institution": "Cam/POLIS",
      "institution_full": "Cambridge — Politics & International Studies (POLIS)",
      "type": "university",
      "region": "UK",
      "date": null,
      "date_end": null,
      "time": null,
      "date_text": "",
      "location": "Cambridge",
      "format": "in-person",
      "topics": [],
      "summary": "Events Events overview POLIS Centre Events Inaugural Lecture Cambridge International Relations and History Conference Annual Lectures History and Politics Seminar Series International Relations Seminar Series POLIS Political Economy Seminar Series Political Thought and Intellectual History Seminar Series Contemporary Political Thought Seminar Series Privacy statement: Registering for an event",
      "first_seen": "2026-05-16",
      "country": "United Kingdom",
      "city": "Cambridge",
      "flag": "🇬🇧",
      "lat": 52.205,
      "lng": 0.119
    },
    {
      "id": "7aee643183b2",
      "title": "Baltic Geopolitics Summer School 2026 – Resilience",
      "url": "https://www.cfg.cam.ac.uk/events/baltic-geopolitics-summer-school-2026-resilience/",
      "source_key": "cam_cfg",
      "institution": "Cam/CfG",
      "institution_full": "Cambridge — Centre for Geopolitics",
      "type": "university",
      "region": "UK",
      "date": null,
      "date_end": null,
      "time": null,
      "date_text": "",
      "location": null,
      "format": "in-person",
      "topics": [
        "China",
        "Japan & Korea",
        "EU & foreign policy",
        "Security & intelligence",
        "Nordic & Baltic"
      ],
      "summary": "Event Diplomacy, Grand Strategy, Politics Friday 19th June, 2026 The Baltic States and Europe’s geopolitical future Event Diplomacy, Grand Strategy Monday 22nd June, 2026 Science diplomacy: How will it upgrade the Korea-Britain global strategic partnership Event Economics, Risk, Security Friday 26th June, 2026 Between de-risking and interdependence: Rethinking Europe-China relations Event Borders,",
      "first_seen": "2026-05-28",
      "country": "United Kingdom",
      "city": "Cambridge",
      "flag": "🇬🇧",
      "lat": 52.205,
      "lng": 0.119
    },
    {
      "id": "43d4d33b1823",
      "title": "Between de-risking and interdependence: Rethinking Europe-China relations",
      "url": "https://www.cfg.cam.ac.uk/events/between-de-risking-and-interdependence-rethinking-europe-china-relations/",
      "source_key": "cam_cfg",
      "institution": "Cam/CfG",
      "institution_full": "Cambridge — Centre for Geopolitics",
      "type": "university",
      "region": "UK",
      "date": null,
      "date_end": null,
      "time": null,
      "date_text": "",
      "location": null,
      "format": "in-person",
      "topics": [
        "China",
        "Japan & Korea",
        "EU & foreign policy",
        "Security & intelligence",
        "Nordic & Baltic"
      ],
      "summary": "Event Diplomacy, Grand Strategy, Politics Friday 19th June, 2026 The Baltic States and Europe’s geopolitical future Event Diplomacy, Grand Strategy Monday 22nd June, 2026 Science diplomacy: How will it upgrade the Korea-Britain global strategic partnership Event Economics, Risk, Security Friday 26th June, 2026 Between de-risking and interdependence: Rethinking Europe-China relations Event Borders,",
      "first_seen": "2026-05-28",
      "country": "United Kingdom",
      "city": "Cambridge",
      "flag": "🇬🇧",
      "lat": 52.205,
      "lng": 0.119
    },
    {
      "id": "c5b8e96809ee",
      "title": "Contemporary Political Thought Seminar Series",
      "url": "https://www.polis.cam.ac.uk/events/contemporary-political-thought-seminar-series",
      "source_key": "cam_polis",
      "institution": "Cam/POLIS",
      "institution_full": "Cambridge — Politics & International Studies (POLIS)",
      "type": "university",
      "region": "UK",
      "date": null,
      "date_end": null,
      "time": null,
      "date_text": "",
      "location": "Cambridge",
      "format": "in-person",
      "topics": [],
      "summary": "Events Events overview POLIS Centre Events Inaugural Lecture Cambridge International Relations and History Conference Annual Lectures History and Politics Seminar Series International Relations Seminar Series POLIS Political Economy Seminar Series Political Thought and Intellectual History Seminar Series Contemporary Political Thought Seminar Series Privacy statement: Registering for an event",
      "first_seen": "2026-05-16",
      "country": "United Kingdom",
      "city": "Cambridge",
      "flag": "🇬🇧",
      "lat": 52.205,
      "lng": 0.119
    },
    {
      "id": "10a0e75565a6",
      "title": "History and Politics Seminar Series",
      "url": "https://www.polis.cam.ac.uk/events/history-and-politics-seminar-series",
      "source_key": "cam_polis",
      "institution": "Cam/POLIS",
      "institution_full": "Cambridge — Politics & International Studies (POLIS)",
      "type": "university",
      "region": "UK",
      "date": null,
      "date_end": null,
      "time": null,
      "date_text": "",
      "location": "Cambridge",
      "format": "in-person",
      "topics": [],
      "summary": "Events Events overview POLIS Centre Events Inaugural Lecture Cambridge International Relations and History Conference Annual Lectures History and Politics Seminar Series International Relations Seminar Series POLIS Political Economy Seminar Series Political Thought and Intellectual History Seminar Series Contemporary Political Thought Seminar Series Privacy statement: Registering for an event",
      "first_seen": "2026-05-16",
      "country": "United Kingdom",
      "city": "Cambridge",
      "flag": "🇬🇧",
      "lat": 52.205,
      "lng": 0.119
    },
    {
      "id": "10d371629ade",
      "title": "International Relations Seminar Series",
      "url": "https://www.polis.cam.ac.uk/events/international-relations-seminar-series",
      "source_key": "cam_polis",
      "institution": "Cam/POLIS",
      "institution_full": "Cambridge — Politics & International Studies (POLIS)",
      "type": "university",
      "region": "UK",
      "date": null,
      "date_end": null,
      "time": null,
      "date_text": "",
      "location": "Cambridge",
      "format": "in-person",
      "topics": [],
      "summary": "Events Events overview POLIS Centre Events Inaugural Lecture Cambridge International Relations and History Conference Annual Lectures History and Politics Seminar Series International Relations Seminar Series POLIS Political Economy Seminar Series Political Thought and Intellectual History Seminar Series Contemporary Political Thought Seminar Series Privacy statement: Registering for an event",
      "first_seen": "2026-05-16",
      "country": "United Kingdom",
      "city": "Cambridge",
      "flag": "🇬🇧",
      "lat": 52.205,
      "lng": 0.119
    },
    {
      "id": "9f19fd3369a0",
      "title": "POLIS Centre Events",
      "url": "https://www.polis.cam.ac.uk/events/polis-centre-events",
      "source_key": "cam_polis",
      "institution": "Cam/POLIS",
      "institution_full": "Cambridge — Politics & International Studies (POLIS)",
      "type": "university",
      "region": "UK",
      "date": null,
      "date_end": null,
      "time": null,
      "date_text": "",
      "location": "Cambridge",
      "format": "in-person",
      "topics": [],
      "summary": "Events Events overview POLIS Centre Events Inaugural Lecture Cambridge International Relations and History Conference Annual Lectures History and Politics Seminar Series International Relations Seminar Series POLIS Political Economy Seminar Series Political Thought and Intellectual History Seminar Series Contemporary Political Thought Seminar Series Privacy statement: Registering for an event",
      "first_seen": "2026-05-16",
      "country": "United Kingdom",
      "city": "Cambridge",
      "flag": "🇬🇧",
      "lat": 52.205,
      "lng": 0.119
    },
    {
      "id": "92c29a8f691b",
      "title": "POLIS Political Economy Seminar Series",
      "url": "https://www.polis.cam.ac.uk/events/polis-political-economy-seminar-series",
      "source_key": "cam_polis",
      "institution": "Cam/POLIS",
      "institution_full": "Cambridge — Politics & International Studies (POLIS)",
      "type": "university",
      "region": "UK",
      "date": null,
      "date_end": null,
      "time": null,
      "date_text": "",
      "location": "Cambridge",
      "format": "in-person",
      "topics": [],
      "summary": "Events Events overview POLIS Centre Events Inaugural Lecture Cambridge International Relations and History Conference Annual Lectures History and Politics Seminar Series International Relations Seminar Series POLIS Political Economy Seminar Series Political Thought and Intellectual History Seminar Series Contemporary Political Thought Seminar Series Privacy statement: Registering for an event",
      "first_seen": "2026-05-16",
      "country": "United Kingdom",
      "city": "Cambridge",
      "flag": "🇬🇧",
      "lat": 52.205,
      "lng": 0.119
    },
    {
      "id": "adbcac8f1f19",
      "title": "Political Thought and Intellectual History Seminar Series",
      "url": "https://www.polis.cam.ac.uk/events/political-thought-and-intellectual-history-seminar-series",
      "source_key": "cam_polis",
      "institution": "Cam/POLIS",
      "institution_full": "Cambridge — Politics & International Studies (POLIS)",
      "type": "university",
      "region": "UK",
      "date": null,
      "date_end": null,
      "time": null,
      "date_text": "",
      "location": "Cambridge",
      "format": "in-person",
      "topics": [],
      "summary": "Events Events overview POLIS Centre Events Inaugural Lecture Cambridge International Relations and History Conference Annual Lectures History and Politics Seminar Series International Relations Seminar Series POLIS Political Economy Seminar Series Political Thought and Intellectual History Seminar Series Contemporary Political Thought Seminar Series Privacy statement: Registering for an event",
      "first_seen": "2026-05-16",
      "country": "United Kingdom",
      "city": "Cambridge",
      "flag": "🇬🇧",
      "lat": 52.205,
      "lng": 0.119
    },
    {
      "id": "3eeef11e409f",
      "title": "Privacy statement: Registering for an event",
      "url": "https://www.polis.cam.ac.uk/events/privacy-statement-registering-event",
      "source_key": "cam_polis",
      "institution": "Cam/POLIS",
      "institution_full": "Cambridge — Politics & International Studies (POLIS)",
      "type": "university",
      "region": "UK",
      "date": null,
      "date_end": null,
      "time": null,
      "date_text": "",
      "location": "Cambridge",
      "format": "in-person",
      "topics": [],
      "summary": "Events Events overview POLIS Centre Events Inaugural Lecture Cambridge International Relations and History Conference Annual Lectures History and Politics Seminar Series International Relations Seminar Series POLIS Political Economy Seminar Series Political Thought and Intellectual History Seminar Series Contemporary Political Thought Seminar Series Privacy statement: Registering for an event",
      "first_seen": "2026-05-16",
      "country": "United Kingdom",
      "city": "Cambridge",
      "flag": "🇬🇧",
      "lat": 52.205,
      "lng": 0.119
    },
    {
      "id": "c2ad4c64d009",
      "title": "SIPRI Lecture",
      "url": "https://www.sipri.org/events/sipri-lecture",
      "source_key": "sipri",
      "institution": "SIPRI",
      "institution_full": "Stockholm International Peace Research Institute",
      "type": "research_institute",
      "region": "Nordic",
      "date": null,
      "date_end": null,
      "time": null,
      "date_text": "",
      "location": "Stockholm",
      "format": "in-person",
      "topics": [
        "Security & intelligence"
      ],
      "summary": "News and Events Past News and Events Upcoming Events SIPRI Lecture Stockholm Forum on Peace and Development Stockholm Security Conference",
      "first_seen": "2026-04-28",
      "country": "Sweden",
      "city": "Stockholm",
      "flag": "🇸🇪",
      "lat": 59.329,
      "lng": 18.069
    },
    {
      "id": "dac36c7f9b97",
      "title": "Science diplomacy: How will it upgrade the Korea-Britain global strategic partnership",
      "url": "https://www.cfg.cam.ac.uk/events/science-diplomacy-how-will-it-upgrade-the-korea-britain-global-strategic-partnership/",
      "source_key": "cam_cfg",
      "institution": "Cam/CfG",
      "institution_full": "Cambridge — Centre for Geopolitics",
      "type": "university",
      "region": "UK",
      "date": null,
      "date_end": null,
      "time": null,
      "date_text": "",
      "location": null,
      "format": "in-person",
      "topics": [
        "China",
        "Japan & Korea",
        "EU & foreign policy",
        "Security & intelligence",
        "Nordic & Baltic"
      ],
      "summary": "Event Diplomacy, Grand Strategy, Politics Friday 19th June, 2026 The Baltic States and Europe’s geopolitical future Event Diplomacy, Grand Strategy Monday 22nd June, 2026 Science diplomacy: How will it upgrade the Korea-Britain global strategic partnership Event Economics, Risk, Security Friday 26th June, 2026 Between de-risking and interdependence: Rethinking Europe-China relations Event Borders,",
      "first_seen": "2026-06-18",
      "country": "United Kingdom",
      "city": "Cambridge",
      "flag": "🇬🇧",
      "lat": 52.205,
      "lng": 0.119
    },
    {
      "id": "8dcf9908cb24",
      "title": "Stockholm Forum on Peace and Development",
      "url": "https://www.sipri.org/events/stockholm-forum-peace-and-development",
      "source_key": "sipri",
      "institution": "SIPRI",
      "institution_full": "Stockholm International Peace Research Institute",
      "type": "research_institute",
      "region": "Nordic",
      "date": null,
      "date_end": null,
      "time": null,
      "date_text": "",
      "location": "Stockholm",
      "format": "in-person",
      "topics": [
        "Security & intelligence"
      ],
      "summary": "News and Events Past News and Events Upcoming Events SIPRI Lecture Stockholm Forum on Peace and Development Stockholm Security Conference",
      "first_seen": "2026-05-13",
      "country": "Sweden",
      "city": "Stockholm",
      "flag": "🇸🇪",
      "lat": 59.329,
      "lng": 18.069
    },
    {
      "id": "a0aa3eca9cca",
      "title": "Stockholm Security Conference",
      "url": "https://www.sipri.org/events/stockholm-security-conference",
      "source_key": "sipri",
      "institution": "SIPRI",
      "institution_full": "Stockholm International Peace Research Institute",
      "type": "research_institute",
      "region": "Nordic",
      "date": null,
      "date_end": null,
      "time": null,
      "date_text": "",
      "location": "Stockholm",
      "format": "in-person",
      "topics": [
        "Security & intelligence"
      ],
      "summary": "News and Events Past News and Events Upcoming Events SIPRI Lecture Stockholm Forum on Peace and Development Stockholm Security Conference",
      "first_seen": "2026-05-13",
      "country": "Sweden",
      "city": "Stockholm",
      "flag": "🇸🇪",
      "lat": 59.329,
      "lng": 18.069
    },
    {
      "id": "d53b13ea96db",
      "title": "The Baltic States and Europe’s geopolitical future",
      "url": "https://www.cfg.cam.ac.uk/events/the-baltic-states-and-europes-geopolitical-future/",
      "source_key": "cam_cfg",
      "institution": "Cam/CfG",
      "institution_full": "Cambridge — Centre for Geopolitics",
      "type": "university",
      "region": "UK",
      "date": null,
      "date_end": null,
      "time": null,
      "date_text": "",
      "location": null,
      "format": "in-person",
      "topics": [
        "China",
        "Japan & Korea",
        "EU & foreign policy",
        "Security & intelligence",
        "Nordic & Baltic"
      ],
      "summary": "Event Diplomacy, Grand Strategy, Politics Friday 19th June, 2026 The Baltic States and Europe’s geopolitical future Event Diplomacy, Grand Strategy Monday 22nd June, 2026 Science diplomacy: How will it upgrade the Korea-Britain global strategic partnership Event Economics, Risk, Security Friday 26th June, 2026 Between de-risking and interdependence: Rethinking Europe-China relations Event Borders,",
      "first_seen": "2026-05-28",
      "country": "United Kingdom",
      "city": "Cambridge",
      "flag": "🇬🇧",
      "lat": 52.205,
      "lng": 0.119
    }
  ]
}